MANIFEST.in
README.md
requirements.txt
setup.cfg
setup.py
dmrandom/__init__.py
dmrandom/index.py
douban_movie_random.egg-info/PKG-INFO
douban_movie_random.egg-info/SOURCES.txt
douban_movie_random.egg-info/dependency_links.txt
douban_movie_random.egg-info/entry_points.txt
douban_movie_random.egg-info/requires.txt
douban_movie_random.egg-info/top_level.txt