Metadata-Version: 1.1
Name: douban-movie-random
Version: 0.0.10
Summary: A simple tool for finding random douban moive of your wishes
Home-page: https://github.com/acwong00/douban-movie-random-py
Author: acwong
Author-email: acwong00@gmail.com
License: MIT
Keywords: movie douban commandline
Platform: UNKNOWN
Classifier: Development Status :: 3 - Alpha
Classifier: License :: OSI Approved :: MIT License
Classifier: Programming Language :: Python :: 3
